[
    {"songCode": 411, "songDescription": "Undercover of the Night"},
    {"songCode": 412, "songDescription": "She Was Hot"},
    {"songCode": 413, "songDescription": "Tie You Up (The Pain of Love)"},
    {"songCode": 414, "songDescription": "Wanna Hold You"},
    {"songCode": 415, "songDescription": "Feel On Baby"},
    {"songCode": 416, "songDescription": "Too Much Blood"},
    {"songCode": 417, "songDescription": "Pretty Beat Up"},
    {"songCode": 418, "songDescription": "Too Tough"},
    {"songCode": 419, "songDescription": "All the Way Down"}
]