[
    {"songCode": 431, "songDescription": "Sad Sad Sad"},
    {"songCode": 432, "songDescription": "Mixed Emotions"},
    {"songCode": 433, "songDescription": "Terrifying"},
    {"songCode": 434, "songDescription": "Hold On to Your Hat"},
    {"songCode": 435, "songDescription": "Hearts for Sale"},
    {"songCode": 436, "songDescription": "Blinded by Love"},
    {"songCode": 437, "songDescription": "Rock and a Hard Place"},
    {"songCode": 438, "songDescription": "Can't Be Seen"},
    {"songCode": 439, "songDescription": "Almost Hear You Sigh"}
]

